auditrum/__init__.py
auditrum/cli.py
auditrum/context.py
auditrum/revert.py
auditrum/schema.py
auditrum/settings.py
auditrum/triggers.py
auditrum/utils.py
auditrum/integrations/__init__.py
auditrum/integrations/django/__init__.py
auditrum/integrations/django/admin.py
auditrum/integrations/django/apps.py
auditrum/integrations/django/audit.py
auditrum/integrations/django/hooks.py
auditrum/integrations/django/middleware.py
auditrum/integrations/django/mixins.py
auditrum/integrations/django/models.py
auditrum/integrations/django/settings.py
auditrum/integrations/django/shell_context.py
auditrum/integrations/django/utils.py
auditrum/integrations/django/management/__init__.py
auditrum/integrations/django/management/commands/__init__.py
auditrum/integrations/django/management/commands/audit_add_partitions.py
auditrum/integrations/django/migrations/0001_initial.py
auditrum/integrations/django/migrations/__init__.py
auditrum/integrations/django/templates/audit/object_history.html
auditrum/integrations/django/templatetags/__init__.py
auditrum/integrations/django/templatetags/audit_tags.py
auditrum-0.2.0.dist-info/licenses/LICENSE
auditrum-0.2.0.dist-info/METADATA
auditrum-0.2.0.dist-info/WHEEL
auditrum-0.2.0.dist-info/entry_points.txt
auditrum-0.2.0.dist-info/top_level.txt
auditrum-0.2.0.dist-info/RECORD
