Metadata-Version: 2.4
Name: auditrum
Version: 0.2.0
Summary: Auditrum — a PostgreSQL audit system with rich contextual logging and Django integration
Author-email: Andrei Karbanovich <andrey.karbanovich@icloud.com>
License: MIT
Project-URL: Homepage, https://github.com/tauvin/auditrum
Project-URL: BugTracker, https://github.com/tauvin/auditrum/issues
Project-URL: Documentation, https://auditrum.readthedocs.io/
Keywords: postgresql,audit,django,database,triggers,history,track changes
Classifier: Development Status :: 4 - Beta
Classifier: Intended Audience :: Developers
Classifier: License :: OSI Approved :: MIT License
Classifier: Programming Language :: Python :: 3
Classifier: Programming Language :: Python :: 3.8
Classifier: Programming Language :: Python :: 3.9
Classifier: Programming Language :: Python :: 3.10
Classifier: Programming Language :: Python :: 3.11
Classifier: Programming Language :: Python :: 3.12
Classifier: Programming Language :: Python :: 3.13
Classifier: Framework :: Django
Classifier: Topic :: Database
Classifier: Topic :: Software Development :: Libraries :: Python Modules
Requires-Python: >=3.8
License-File: LICENSE
Requires-Dist: typer>=0.9
Requires-Dist: psycopg[binary]>=3.1
Requires-Dist: pydantic>=2.5
Requires-Dist: structlog>=23.0
Requires-Dist: dateutils>=0.6.12
Requires-Dist: dotenv>=0.9.9
Provides-Extra: django
Requires-Dist: Django>=4.2; extra == "django"
Dynamic: license-file
